sure_vis/__init__.py
sure_vis/sure.py
sure_vis/surrogate_rule/__init__.py
sure_vis/surrogate_rule/behavior_rule.py
sure_vis/surrogate_rule/error_rule.py
sure_vis/surrogate_rule/forest_info.py
sure_vis/surrogate_rule/tree_node_info.py
sure_vis/vis/dist/sure.js
sure_vis-0.0.1.dist-info/LICENSE.md
sure_vis-0.0.1.dist-info/METADATA
sure_vis-0.0.1.dist-info/WHEEL
sure_vis-0.0.1.dist-info/top_level.txt
sure_vis-0.0.1.dist-info/RECORD
